pysonde-0.0.7.dist-info/METADATA
pysonde-0.0.7.dist-info/WHEEL
pysonde-0.0.7.dist-info/entry_points.txt
pysonde-0.0.7.dist-info/licenses/LICENSE
pysonde/__init__.py
pysonde/__main__.py
pysonde/_dataset_creator.py
pysonde/_helpers.py
pysonde/_proc_level2.py
pysonde/make_quicklooks_rs41.py
pysonde/make_skewT.py
pysonde/meteorology_helpers.py
pysonde/pysonde.py
pysonde/readers/__init__.py
pysonde/readers/reader_helpers.py
pysonde/readers/readers.py
pysonde/sounding.py
pysonde/thermodynamics.py
test/__init__.py
test/json/legacyrecord.json
test/test_cor_output.py
test/test_mwx_output.py
test/test_pysonde.py
pysonde-0.0.7.dist-info/RECORD
