Metadata-Version: 2.1
Name: pysonde
Version: 0.0.7
Summary: Post-processing tool for atmospheric sounding data
Author-Email: Hauke Schulz <43613877+observingClouds@users.noreply.github.com>
License: MIT
Classifier: Development Status :: 3 - Alpha
Classifier: Environment :: Console
Classifier: Intended Audience :: Developers
Classifier: License :: OSI Approved :: MIT License
Classifier: Programming Language :: Python :: 3.10
Classifier: Programming Language :: Python :: 3.11
Classifier: Programming Language :: Python :: 3.12
Classifier: Programming Language :: Python :: 3.9
Project-URL: Homepage, https://github.com/observingClouds/pysonde
Requires-Python: >=3.9
Requires-Dist: cartopy
Requires-Dist: coverage
Requires-Dist: bottleneck
Requires-Dist: dask
Requires-Dist: metpy
Requires-Dist: netCDF4
Requires-Dist: numpy
Requires-Dist: omegaconf
Requires-Dist: pandas
Requires-Dist: pdm-backend
Requires-Dist: Pint
Requires-Dist: Pint-Pandas
Requires-Dist: pint-xarray
Requires-Dist: PyYAML
Requires-Dist: regex
Requires-Dist: tqdm
Requires-Dist: xarray
Requires-Dist: geopy
Provides-Extra: dev
Requires-Dist: black; extra == "dev"
Requires-Dist: flake8; extra == "dev"
Requires-Dist: isort; extra == "dev"
Requires-Dist: mock; extra == "dev"
Requires-Dist: mypy; extra == "dev"
Requires-Dist: pre-commit; extra == "dev"
Requires-Dist: pylint; extra == "dev"
Requires-Dist: pytest; extra == "dev"
Requires-Dist: pytest-cov; extra == "dev"
Requires-Dist: pytest-lazy-fixture; extra == "dev"
Requires-Dist: yapf; extra == "dev"
